socialcommons/__init__.py
socialcommons/browser.py
socialcommons/clarifai_util.py
socialcommons/database_engine.py
socialcommons/exceptions.py
socialcommons/file_manager.py
socialcommons/print_log_writer.py
socialcommons/quota_supervisor.py
socialcommons/text_analytics.py
socialcommons/time_util.py
socialcommons/util.py
SocialCommons-0.0.5.dist-info/LICENSE.txt
SocialCommons-0.0.5.dist-info/METADATA
SocialCommons-0.0.5.dist-info/WHEEL
SocialCommons-0.0.5.dist-info/top_level.txt
SocialCommons-0.0.5.dist-info/RECORD
