Metadata-Version: 2.1
Name: SocialCommons
Version: 0.0.5
Summary: Common library for all XPy bots under socialbotspy
Home-page: UNKNOWN
Author: Ishan Dutta
Author-email: ishandutta2007@gmail.com
License: Creative Commons Attribution-Noncommercial-Share Alike license
Platform: UNKNOWN
Requires-Dist: MeaningCloud-python (==1.1.1)
Requires-Dist: clarifai (==2.5.2)
Requires-Dist: emoji (==0.5.1)
Requires-Dist: instapy-chromedriver (==2.44)
Requires-Dist: pathlib (==1.0.1)
Requires-Dist: plyer (==1.4.0)
Requires-Dist: regex (==2019.2.7)
Requires-Dist: requests (==2.21.0)
Requires-Dist: selenium (==3.141.0)
Requires-Dist: setuptools (==41.0.1)
Requires-Dist: wheel (==0.33.6)
